{
  "msg": "Success",
  "code": "200",
  "data": [
    {
      "desc": "序号",
      "key": "number",
      "data": [1, 2, 3, 4, 5, 6, 7, 8, 9, 10]
    },
    {
      "desc": "请假幼儿",
      "key": "holidayChildren",
      "data": ["鞠婧祎", "范冰冰", "杰克马", "鸡儿", "漩涡向日葵", "漩涡博人", "钟意", "玄冥二老", "圣斗士", "李元芳"]
    },
    {
      "desc": "所在班级",
      "key": "currentClass",
      "data": ["朗云小班", "朗云小班", "朗云小班", "朗云小班", "朗云小班", "朗云小班", "朗云小班", "朗云小班", "朗云小班", "朗云小班"]
    },
    {
      "desc": "请假时间",
      "key": "holidaySpan",
      "data": [
        {
          "start_time": "2020-11-1",
          "end_time": "2020-11-10"
        },
        {
          "start_time": "2020-11-30",
          "end_time": "2020-11-30"
        },
        {
          "start_time": "2020-10-9",
          "end_time": "2020-10-16"
        },
        {
          "start_time": "2020-11-1",
          "end_time": "2020-11-3"
        },
        {
          "start_time": "2020-12-2",
          "end_time": "2020-12-8"
        },
        {
          "start_time": "2020-9-2",
          "end_time": "2020-9-5"
        },
        {
          "start_time": "2020-12-1",
          "end_time": "2020-12-10"
        },
        {
          "start_time": "2020-9-26",
          "end_time": "2020-9-28"
        },
        {
          "start_time": "2020-10-28",
          "end_time": "2020-11-1"
        },
        {
          "start_time": "2020-11-11",
          "end_time": "2020-11-13"
        }
      ]
    },
    {
      "desc": "内容",
      "key": "content",
      "data": [
        "暂无内容",
        "暂无内容",
        "暂无内容",
        "暂无内容",
        "暂无内容",
        "暂无内容",
        "暂无内容",
        "暂无内容",
        "暂无内容",
        "暂无内容"
      ]
    },
    {
      "desc": "提交时间",
      "key": "submitTime",
      "data": [
        "2020-10-30",
        "2020-11-29",
        "2020-10-8",
        "2020-10-30",
        "2020-10-29",
        "2020-9-1",
        "2020-11-29",
        "2020-9-24",
        "2020-10-27",
        "2020-11-11"
      ]
    }
  ]
}
